{
  "users": [
    {
      "id": 1,
      "orderNo": "600101",
      "userName": "Alice",
      "status": "",
      "stall": [
        {
          "stallNo": "Stall #03",
          "items": [
            {
              "name": "Medium Veggie Burger",
              "Quantity": 2
            },
            {
              "name": "Small Fries",
              "Quantity": 1
            }
          ]
        },
        {
          "stallNo": "Stall #05",
          "items": [
            {
              "name": "Medium Iced Tea",
              "Quantity": 1
            },
            {
              "name": "Chicken Sushi",
              "Quantity": 2
            }
          ]
        }
      ]
    },
    {
      "id": 2,
      "orderNo": "600102",
      "userName": "Bob",
      "status": "",
      "stall": [
        {
          "stallNo": "Stall #02",
          "items": [
            {
              "name": "Large Margherita Pizza",
              "Quantity": 1
            },
            {
              "name": "Cheese Garlic Bread",
              "Quantity": 1
            }
          ]
        },
        {
          "stallNo": "Stall #06",
          "items": [
            {
              "name": "Large Pepsi",
              "Quantity": 2
            },
            {
              "name": "Vegetable Spring Rolls",
              "Quantity": 3
            }
          ]
        }
      ]
    },
    {
      "id": 3,
      "orderNo": "600103",
      "userName": "Charlie",
      "status": "",
      "stall": [
        {
          "stallNo": "Stall #01",
          "items": [
            {
              "name": "Medium Chicken Pizza",
              "Quantity": 3
            },
            {
              "name": "Fried Rice",
              "Quantity": 2
            }
          ]
        },
        {
          "stallNo": "Stall #04",
          "items": [
            {
              "name": "Large Coke",
              "Quantity": 1
            },
            {
              "name": "Spicy Chicken Wings",
              "Quantity": 4
            }
          ]
        }
      ]
    },
    {
      "id": 4,
      "orderNo": "600104",
      "userName": "David",
      "status": "",
      "stall": [
        {
          "stallNo": "Stall #03",
          "items": [
            {
              "name": "Small Veggie Pizza",
              "Quantity": 4
            },
            {
              "name": "Cheese Sticks",
              "Quantity": 3
            }
          ]
        },
        {
          "stallNo": "Stall #05",
          "items": [
            {
              "name": "Small Sprite",
              "Quantity": 5
            },
            {
              "name": "Vegetable Samosa",
              "Quantity": 7
            }
          ]
        }
      ]
    },
    {
      "id": 7,
      "orderNo": "600105",
      "userName": "Eva",
      "status": "",
      "stall": [
        {
          "stallNo": "Stall #02",
          "items": [
            {
              "name": "Medium Pepperoni Pizza",
              "Quantity": 1
            },
            {
              "name": "Caesar Salad",
              "Quantity": 3
            }
          ]
        },
        {
          "stallNo": "Stall #06",
          "items": [
            {
              "name": "Large Mountain Dew",
              "Quantity": 2
            },
            {
              "name": "Shrimp Tempura",
              "Quantity": 2
            }
          ]
        }
      ]
    },
    {
      "id": 8,
      "orderNo": "600106",
      "userName": "John",
      "status": "",
      "stall": [
        {
          "stallNo": "Stall  #03",
          "items": [
            {
              "name": "Small Veggie Pizza",
              "Quantity": 1
            },
            {
              "name": "Cheese Sticks",
              "Quantity": 3
            }
          ]
        },
        {
          "stallNo": "Stall #05",
          "items": [
            {
              "name": "Small Sprite",
              "Quantity": 3
            },
            {
              "name": "Vegetable Samosa",
              "Quantity": 2
            }
          ]
        }
      ]
    }
    
  ]
}